smartrun/__init__.py
smartrun/check_packages.py
smartrun/cli.py
smartrun/comments.py
smartrun/help_.py
smartrun/known_mappings.py
smartrun/local_requests.py
smartrun/options.py
smartrun/package_name.py
smartrun/runner.py
smartrun/runner_helpers.py
smartrun/scan_imports.py
smartrun/smart_runner.py
smartrun/subprocess_.py
smartrun/utils.py
smartrun/envc/__init__.py
smartrun/envc/envc.py
smartrun/envc/envc2.py
smartrun/installers/__init__.py
smartrun/installers/from_json.py
smartrun/installers/from_json_fast.py
smartrun/installers/from_yaml.py
smartrun/nb/__init__.py
smartrun/nb/nb_run.py
smartrun-1.1.3.dist-info/METADATA
smartrun-1.1.3.dist-info/WHEEL
smartrun-1.1.3.dist-info/entry_points.txt
smartrun-1.1.3.dist-info/licenses/LICENSE
smartrun-1.1.3.dist-info/RECORD
