Metadata-Version: 2.4
Name: smartrun
Version: 1.1.3
Summary: Run any Python script with automatic environment setup, fast package resolution via uv, and reproducible lockfile generation
Project-URL: Repository, https://github.com/SermetPekin/smartrun
Project-URL: Homepage, https://github.com/SermetPekin/smartrun
Project-URL: Documentation, https://smartrun.readthedocs.io/en/latest/home.html
Project-URL: Issues, https://github.com/SermetPekin/smartrun/issues
Project-URL: Changelog, https://github.com/SermetPekin/smartrun/releases
Author-email: Sermet Pekin <Sermet.Pekin@gmail.com>
License: BSD 3-Clause License
License-File: LICENSE
Classifier: License :: OSI Approved :: BSD License
Requires-Python: >=3.10
Requires-Dist: nbformat>=5.10.4
Requires-Dist: pip-tools>=7.4.1
Requires-Dist: pyyaml>=6.0.2
Requires-Dist: rich>=14.0.0
Requires-Dist: uv>=0.7.21
Provides-Extra: dev
Requires-Dist: black>=25.1.0; extra == 'dev'
Requires-Dist: flake8>=7.3.0; extra == 'dev'
Requires-Dist: myst-parser>=4.0.1; extra == 'dev'
Requires-Dist: pytest>=8.4.1; extra == 'dev'
Requires-Dist: ruff>=0.12.3; extra == 'dev'
Provides-Extra: jupyter
Requires-Dist: ipykernel>=6.30.0; extra == 'jupyter'
Requires-Dist: nbconvert>=7.0.0; extra == 'jupyter'
Requires-Dist: nbformat>=5.10.4; extra == 'jupyter'
